spoon_toolkits/__init__.py
spoon_toolkits/audio/__init__.py
spoon_toolkits/audio/elevenlabs_tools.py
spoon_toolkits/audio/test_elevenlabs.py
spoon_toolkits/crypto/crypto_data_tools/__init__.py
spoon_toolkits/crypto/crypto_data_tools/base.py
spoon_toolkits/crypto/crypto_data_tools/blockchain_monitor.py
spoon_toolkits/crypto/crypto_data_tools/lending_rates.py
spoon_toolkits/crypto/crypto_data_tools/predict_price.py
spoon_toolkits/crypto/crypto_data_tools/price_alerts.py
spoon_toolkits/crypto/crypto_data_tools/price_data.py
spoon_toolkits/crypto/crypto_data_tools/token_holders.py
spoon_toolkits/crypto/crypto_data_tools/trading_history.py
spoon_toolkits/crypto/crypto_data_tools/uniswap_liquidity.py
spoon_toolkits/crypto/crypto_data_tools/wallet_analysis.py
spoon_toolkits/crypto/crypto_powerdata/__init__.py
spoon_toolkits/crypto/crypto_powerdata/data_provider.py
spoon_toolkits/crypto/crypto_powerdata/dual_transport_server.py
spoon_toolkits/crypto/crypto_powerdata/enhanced_indicators.py
spoon_toolkits/crypto/crypto_powerdata/main.py
spoon_toolkits/crypto/crypto_powerdata/mcp_bridge.py
spoon_toolkits/crypto/crypto_powerdata/server.py
spoon_toolkits/crypto/crypto_powerdata/talib_registry.py
spoon_toolkits/crypto/crypto_powerdata/tools.py
spoon_toolkits/crypto/evm/__init__.py
spoon_toolkits/crypto/evm/balance.py
spoon_toolkits/crypto/evm/bridge.py
spoon_toolkits/crypto/evm/erc20.py
spoon_toolkits/crypto/evm/quote.py
spoon_toolkits/crypto/evm/signers.py
spoon_toolkits/crypto/evm/swap.py
spoon_toolkits/crypto/evm/transfer.py
spoon_toolkits/crypto/neo/__init__.py
spoon_toolkits/crypto/neo/address_tools.py
spoon_toolkits/crypto/neo/asset_tools.py
spoon_toolkits/crypto/neo/base.py
spoon_toolkits/crypto/neo/block_tools.py
spoon_toolkits/crypto/neo/contract_tools.py
spoon_toolkits/crypto/neo/governance_tools.py
spoon_toolkits/crypto/neo/log_state_tools.py
spoon_toolkits/crypto/neo/neo_provider.py
spoon_toolkits/crypto/neo/nep_tools.py
spoon_toolkits/crypto/neo/sc_call_tools.py
spoon_toolkits-0.2.5.dist-info/licenses/LICENSE
spoon_toolkits-0.2.5.dist-info/METADATA
spoon_toolkits-0.2.5.dist-info/WHEEL
spoon_toolkits-0.2.5.dist-info/top_level.txt
spoon_toolkits-0.2.5.dist-info/RECORD
