Metadata-Version: 2.4
Name: spoon-toolkits
Version: 0.2.5
Summary: Comprehensive blockchain and cryptocurrency tools for SpoonAI
Author-email: SpoonAI Team <team@spoonai.com>
Project-URL: Homepage, https://github.com/XSpoonAi/spoon-toolkits
Project-URL: Bug Tracker, https://github.com/XSpoonAi/spoon-toolkits/issues
Classifier: Programming Language :: Python :: 3
Classifier: License :: OSI Approved :: MIT License
Classifier: Operating System :: OS Independent
Requires-Python: >=3.12
License-File: LICENSE
Requires-Dist: requests>=2.32.3
Requires-Dist: aiohttp>=3.13.2
Requires-Dist: pycares<5.0,>=4.9
Requires-Dist: fastmcp>=2.12.0
Requires-Dist: pandas>=2.2.0
Requires-Dist: httpx>=0.28.1
Requires-Dist: beautifulsoup4>=4.12.3
Requires-Dist: markdownify>=0.11.6
Requires-Dist: pydantic>=2.10.4
Requires-Dist: python-dotenv>=1.0.1
Requires-Dist: typing-extensions>=4.12.2
Requires-Dist: nest-asyncio>=1.6.0
Requires-Dist: base58>=2.1.1
Requires-Dist: PyNaCl>=1.5.0
Requires-Dist: web3==7.11.0
Requires-Dist: solana>=0.33.0
Requires-Dist: solders>=0.19.0
Requires-Dist: neo-mamba<3.2.0,>=3.0.1; python_version < "3.14"
Requires-Dist: neo-mamba>=3.2.0; python_version == "3.14"
Requires-Dist: ccxt>=4.0.0
Requires-Dist: numpy>=1.26.0
Requires-Dist: TA-Lib>=0.6.5
Requires-Dist: asyncio-throttle>=1.0.0
Requires-Dist: pydantic-settings>=2.0.0
Requires-Dist: fastapi>=0.115.7
Requires-Dist: uvicorn[standard]>=0.32.0
Requires-Dist: boto3==1.35.99
Requires-Dist: desearch-py>=1.0.0
Requires-Dist: scikit-learn>=1.4.2
Requires-Dist: gql>=3.5.0
Requires-Dist: elevenlabs>=1.0.0
Dynamic: license-file
